common/__init__.py
common/constants.py
skyeye/__init__.py
skyeye/web/__init__.py
skyeye/web/middleware/__init__.py
skyeye/web/middleware/fastapi.py
skyeye/web/middleware/otel.py
skyeye_python_instrumentator-0.2.20.dist-info/METADATA
skyeye_python_instrumentator-0.2.20.dist-info/WHEEL
skyeye_python_instrumentator-0.2.20.dist-info/top_level.txt
skyeye_python_instrumentator-0.2.20.dist-info/RECORD
